PyEngine_3D_v3/Constants.py
PyEngine_3D_v3/Map.py
PyEngine_3D_v3/Object3D.py
PyEngine_3D_v3/Player.py
PyEngine_3D_v3/Point.py
PyEngine_3D_v3/Polygon.py
PyEngine_3D_v3/__init__.py
PyEngine_3D_v3-3.1.dist-info/METADATA
PyEngine_3D_v3-3.1.dist-info/WHEEL
PyEngine_3D_v3-3.1.dist-info/top_level.txt
PyEngine_3D_v3-3.1.dist-info/RECORD
