Metadata-Version: 2.1
Name: PyEngine_3D_v3
Version: 3.1
Summary: 3D-engine for Python.
Author-email: v6577295@gmail.com
Requires-Python: >=3.10
